MoinMoin/Page.py
MoinMoin/PageEditor.py
MoinMoin/PageGraphicalEditor.py
MoinMoin/__init__.py
MoinMoin/_template.py
MoinMoin/action/AttachFile.py
MoinMoin/action/CopyPage.py
MoinMoin/action/DeletePage.py
MoinMoin/action/Despam.py
MoinMoin/action/LikePages.py
MoinMoin/action/Load.py
MoinMoin/action/LocalSiteMap.py
MoinMoin/action/MyPages.py
MoinMoin/action/PackagePages.py
MoinMoin/action/RenamePage.py
MoinMoin/action/RenderAsDocbook.py
MoinMoin/action/Save.py
MoinMoin/action/SlideShow.py
MoinMoin/action/SpellCheck.py
MoinMoin/action/SubscribeUser.py
MoinMoin/action/SyncPages.py
MoinMoin/action/__init__.py
MoinMoin/action/anywikidraw.py
MoinMoin/action/backup.py
MoinMoin/action/bookmark.py
MoinMoin/action/cache.py
MoinMoin/action/chart.py
MoinMoin/action/diff.py
MoinMoin/action/edit.py
MoinMoin/action/fckdialog.py
MoinMoin/action/fullsearch.py
MoinMoin/action/info.py
MoinMoin/action/language_setup.py
MoinMoin/action/links.py
MoinMoin/action/login.py
MoinMoin/action/logout.py
MoinMoin/action/newaccount.py
MoinMoin/action/newpage.py
MoinMoin/action/pollsistersites.py
MoinMoin/action/quicklink.py
MoinMoin/action/quickunlink.py
MoinMoin/action/recoverpass.py
MoinMoin/action/refresh.py
MoinMoin/action/revert.py
MoinMoin/action/rss_rc.py
MoinMoin/action/serveopenid.py
MoinMoin/action/showtags.py
MoinMoin/action/sisterpages.py
MoinMoin/action/sitemap.py
MoinMoin/action/subscribe.py
MoinMoin/action/supplementation.py
MoinMoin/action/thread_monitor.py
MoinMoin/action/titleindex.py
MoinMoin/action/twikidraw.py
MoinMoin/action/unsubscribe.py
MoinMoin/action/userprefs.py
MoinMoin/action/userprofile.py
MoinMoin/auth/_PHPsessionParser.py
MoinMoin/auth/__init__.py
MoinMoin/auth/botbouncer.py
MoinMoin/auth/cas.py
MoinMoin/auth/http.py
MoinMoin/auth/interwiki.py
MoinMoin/auth/ldap_login.py
MoinMoin/auth/log.py
MoinMoin/auth/mysql_group.py
MoinMoin/auth/openidrp.py
MoinMoin/auth/openidrp_ext/__init__.py
MoinMoin/auth/openidrp_ext/openidrp_sreg.py
py3moin-3.0.0a1.dist-info/LICENSE
py3moin-3.0.0a1.dist-info/METADATA
py3moin-3.0.0a1.dist-info/WHEEL
py3moin-3.0.0a1.dist-info/entry_points.txt
py3moin-3.0.0a1.dist-info/RECORD
