Metadata-Version: 2.1
Name: py3moin
Version: 3.0.0a1
Summary: 
Author: Zhongke Chen
Author-email: ch3n2k@gmail.com
Requires-Python: >=3.9,<4.0
Classifier: Programming Language :: Python :: 3
Classifier: Programming Language :: Python :: 3.9
Classifier: Programming Language :: Python :: 3.10
Classifier: Programming Language :: Python :: 3.11
Requires-Dist: flup (>=1.0,<2.0)
Requires-Dist: future (>=0.18,<0.19)
Requires-Dist: html-sanitizer (>=1.9,<2.0)
Requires-Dist: parsedatetime (>=2.6,<3.0)
Requires-Dist: passlib (>=1.7,<2.0)
Requires-Dist: pygments (>=2.15,<3.0)
Requires-Dist: pytest (>=7.2,<8.0)
Requires-Dist: secure-cookie (>=0.2.0,<0.3.0)
Requires-Dist: werkzeug (>=2.2.3,<3.0.0)
